src/__init__.py
src/file.py
src/obj_to_stl/__init__.py
src/obj_to_stl/normal_vertex.py
src/obj_to_stl/obj_reader.py
src/obj_to_stl/obj_stl_convertor.py
src/obj_to_stl/run_obj_to_stl.py
src/obj_to_stl/stl_writer.py
src/stl_to_obj/__init__.py
src/stl_to_obj/obj_writer.py
src/stl_to_obj/run_stl_to_obj.py
src/stl_to_obj/stl_obj_convertor.py
src/stl_to_obj/stl_reader.py
stl_obj_convertor/__init__.py
stl_obj_convertor/convertor.py
test/__init__.py
test/test_obj_reader.py
test/test_obj_stl_convertor.py
test/test_obj_writer.py
test/test_stl_obj_convertor.py
test/test_stl_reader.py
test/test_stl_writer.py
test/test_data/__init__.py
test/test_data/cube.obj
test/test_data/expected.obj
test/test_data/expected.stl
test/test_data/result.obj
test/test_data/result.stl
test/test_data/test_cube.stl
utilis/__init__.py
utilis/progressbar.py
stl_obj_convertor-0.3.0.dist-info/LICENSE
stl_obj_convertor-0.3.0.dist-info/METADATA
stl_obj_convertor-0.3.0.dist-info/WHEEL
stl_obj_convertor-0.3.0.dist-info/top_level.txt
stl_obj_convertor-0.3.0.dist-info/RECORD
